consentcrawl/__init__.py
consentcrawl/__main__.py
consentcrawl/assets/blocklists.yml
consentcrawl/assets/consent_managers.yml
consentcrawl/blocklists.py
consentcrawl/cli.py
consentcrawl/crawl.py
consentcrawl/utils.py
consentcrawl-0.1.4.dist-info/LICENSE
consentcrawl-0.1.4.dist-info/METADATA
consentcrawl-0.1.4.dist-info/WHEEL
consentcrawl-0.1.4.dist-info/entry_points.txt
consentcrawl-0.1.4.dist-info/RECORD
