Metadata-Version: 2.1
Name: consentcrawl
Version: 0.1.4
Summary: Automatically check for GDPR/CCPA consent by running a Playwright headless browser to check for marketing and analytics scripts firing before and after consent.
Home-page: https://github.com/dumkydewilde/consentcrawl/
License: MIT
Author: Dumky de Wilde
Requires-Python: >=3.10,<4.0
Classifier: Development Status :: 3 - Alpha
Classifier: Environment :: Console
Classifier: License :: OSI Approved :: MIT License
Classifier: Programming Language :: Python :: 3
Classifier: Programming Language :: Python :: 3.10
Classifier: Programming Language :: Python :: 3.11
Classifier: Programming Language :: Python :: 3.12
Classifier: Topic :: Internet
Classifier: Topic :: Internet :: WWW/HTTP :: Site Management
Classifier: Topic :: Software Development :: Libraries
Requires-Dist: playwright (>=1.34,<2.0)
Requires-Dist: pyyaml (>=6.0.1,<7.0.0)
Requires-Dist: requests (>=2.31.0,<3.0.0)
Project-URL: Documentation, https://github.com/dumkydewilde/consentcrawl/main/README.md
Project-URL: Repository, https://github.com/dumkydewilde/consentcrawl/
